streamlit_hotkeys/__init__.py
streamlit_hotkeys/manager.py
streamlit_hotkeys/component/__init__.py
streamlit_hotkeys/component/index.html
streamlit_hotkeys/component/index.js
streamlit_hotkeys/component/streamlit-component-lib.js
streamlit_hotkeys-0.6.0.dist-info/licenses/LICENSE
streamlit_hotkeys-0.6.0.dist-info/METADATA
streamlit_hotkeys-0.6.0.dist-info/WHEEL
streamlit_hotkeys-0.6.0.dist-info/top_level.txt
streamlit_hotkeys-0.6.0.dist-info/RECORD
