Metadata-Version: 2.4
Name: streamlit-hotkeys
Version: 0.6.0
Summary: Keyboard hotkeys for Streamlit (Ctrl/Cmd/Alt/Shift combos) with edge-triggered events.
Author-email: Viktor Shcherbakov <viktoroo.sch@gmail.com>
Maintainer-email: Viktor Shcherbakov <viktoroo.sch@gmail.com>
License: MIT License
Project-URL: Source, https://github.com/viktor-shcherb/streamlit-hotkeys
Project-URL: Issue Tracker, https://github.com/viktor-shcherb/streamlit-hotkeys/issues
Project-URL: Similar: streamlit-keypress, https://pypi.org/project/streamlit-keypress/
Project-URL: Similar: streamlit-shortcuts, https://pypi.org/project/streamlit-shortcuts/
Project-URL: Similar: streamlit-keyup, https://pypi.org/project/streamlit-keyup/
Project-URL: Similar: keyboard_to_url, https://arnaudmiribel.github.io/streamlit-extras/extras/keyboard_url/
Keywords: streamlit,hotkeys,shortcuts,keyboard,keypress,component
Classifier: Development Status :: 4 - Beta
Classifier: Intended Audience :: Developers
Classifier: Topic :: Software Development :: Libraries :: Application Frameworks
Classifier: License :: OSI Approved :: MIT License
Classifier: Programming Language :: Python
Classifier: Programming Language :: Python :: 3
Classifier: Programming Language :: Python :: 3 :: Only
Classifier: Operating System :: OS Independent
Requires-Python: >=3.8
License-File: LICENSE
Requires-Dist: streamlit>=1.25.0
Dynamic: license-file
